imod/__init__.py
imod/bibtex.py
imod/constants.py
imod/file_handlers.py
imod/icon.png
imod/protocols.conf
imod/utils.py
imod/wizards.py
imod/protocols/__init__.py
imod/protocols/protocol_applyTransformationMatrix.py
imod/protocols/protocol_base.py
imod/protocols/protocol_base_preprocess.py
imod/protocols/protocol_base_ts_align.py
imod/protocols/protocol_batch_run_tomo.py
imod/protocols/protocol_ctfCorrection.py
imod/protocols/protocol_ctfEstimation_automatic.py
imod/protocols/protocol_ctfEstimation_manual.py
imod/protocols/protocol_doseFilter.py
imod/protocols/protocol_etomo.py
imod/protocols/protocol_excludeViews.py
imod/protocols/protocol_fiducialAlignment.py
imod/protocols/protocol_fiducialModel.py
imod/protocols/protocol_goldBeadPicker3d.py
imod/protocols/protocol_importSetOfTM.py
imod/protocols/protocol_tomoPreprocess.py
imod/protocols/protocol_tomoProjection.py
imod/protocols/protocol_tomoReconstruction.py
imod/protocols/protocol_tsPreprocess.py
imod/protocols/protocol_xCorrPrealignment.py
imod/protocols/protocol_xRaysEraser.py
imod/templates/automatic_tilt_series_alignment.json.template
imod/tests/__init__.py
imod/tests/tests_imod.py
imod/tests/tests_imod_workflows.py
imod/viewers/__init__.py
imod/viewers/viewers.py
imod/viewers/views_tkinter_tree.py
scipion_em_imod-3.7.0.dist-info/LICENSE
scipion_em_imod-3.7.0.dist-info/METADATA
scipion_em_imod-3.7.0.dist-info/WHEEL
scipion_em_imod-3.7.0.dist-info/entry_points.txt
scipion_em_imod-3.7.0.dist-info/top_level.txt
scipion_em_imod-3.7.0.dist-info/RECORD
