Metadata-Version: 2.1
Name: scipion-em-imod
Version: 3.7.0
Summary: Plugin to use imod within the Scipion framework
Author-email: Scipion Team <scipion@cnb.csic.es>
License: GNU General Public License v3 (GPLv3)
Project-URL: Homepage, https://github.com/scipion-em/scipion-em-imod
Project-URL: Issues, https://github.com/scipion-em/scipion-em-imod/issues
Keywords: scipion,cryoem,cryoet,imageprocessing,scipion-3.0
Classifier: Development Status :: 4 - Beta
Classifier: License :: OSI Approved :: GNU General Public License v3 (GPLv3)
Classifier: Programming Language :: Python :: 3
Requires-Python: >=3.8
License-File: LICENSE
Requires-Dist: scipion-em-tomo>=3.9.1
